README.md
setup.py
scraly_pulumi_ovh/__init__.py
scraly_pulumi_ovh/_utilities.py
scraly_pulumi_ovh/get_installation_templates.py
scraly_pulumi_ovh/get_server.py
scraly_pulumi_ovh/get_servers.py
scraly_pulumi_ovh/get_vrack_networks.py
scraly_pulumi_ovh/outputs.py
scraly_pulumi_ovh/provider.py
scraly_pulumi_ovh/pulumi-plugin.json
scraly_pulumi_ovh/py.typed
scraly_pulumi_ovh.egg-info/PKG-INFO
scraly_pulumi_ovh.egg-info/SOURCES.txt
scraly_pulumi_ovh.egg-info/dependency_links.txt
scraly_pulumi_ovh.egg-info/not-zip-safe
scraly_pulumi_ovh.egg-info/requires.txt
scraly_pulumi_ovh.egg-info/top_level.txt
scraly_pulumi_ovh/cloudproject/__init__.py
scraly_pulumi_ovh/cloudproject/_inputs.py
scraly_pulumi_ovh/cloudproject/container_registry.py
scraly_pulumi_ovh/cloudproject/container_registry_user.py
scraly_pulumi_ovh/cloudproject/database.py
scraly_pulumi_ovh/cloudproject/failover_ip_attach.py
scraly_pulumi_ovh/cloudproject/get_capabilities_container_filter.py
scraly_pulumi_ovh/cloudproject/get_capabilities_container_registry.py
scraly_pulumi_ovh/cloudproject/get_container_registries.py
scraly_pulumi_ovh/cloudproject/get_container_registry.py
scraly_pulumi_ovh/cloudproject/get_container_registry_users.py
scraly_pulumi_ovh/cloudproject/get_failover_ip_attach.py
scraly_pulumi_ovh/cloudproject/get_kube.py
scraly_pulumi_ovh/cloudproject/get_kube_ip_restrictions.py
scraly_pulumi_ovh/cloudproject/get_kube_node_pool.py
scraly_pulumi_ovh/cloudproject/get_kube_node_pool_nodes.py
scraly_pulumi_ovh/cloudproject/get_kube_nodes.py
scraly_pulumi_ovh/cloudproject/get_kube_oidc.py
scraly_pulumi_ovh/cloudproject/get_m3db_namespace.py
scraly_pulumi_ovh/cloudproject/get_m3db_namespaces.py
scraly_pulumi_ovh/cloudproject/get_m3db_user.py
scraly_pulumi_ovh/cloudproject/get_mongo_db_user.py
scraly_pulumi_ovh/cloudproject/get_open_search_pattern.py
scraly_pulumi_ovh/cloudproject/get_open_search_patterns.py
scraly_pulumi_ovh/cloudproject/get_open_search_user.py
scraly_pulumi_ovh/cloudproject/get_redis_user.py
scraly_pulumi_ovh/cloudproject/get_region.py
scraly_pulumi_ovh/cloudproject/get_regions.py
scraly_pulumi_ovh/cloudproject/get_user.py
scraly_pulumi_ovh/cloudproject/get_user_s3_credential.py
